CHANGES.rst
CONTRIBUTORS.rst
MANIFEST.in
README.rst
setup.cfg
setup.py
docs/LICENSE.GPL
docs/LICENSE.rst
docs/export_screenshot.png
docs/index.rst
src/collective/__init__.py
src/collective.contentexport.egg-info/PKG-INFO
src/collective.contentexport.egg-info/SOURCES.txt
src/collective.contentexport.egg-info/dependency_links.txt
src/collective.contentexport.egg-info/entry_points.txt
src/collective.contentexport.egg-info/namespace_packages.txt
src/collective.contentexport.egg-info/not-zip-safe
src/collective.contentexport.egg-info/requires.txt
src/collective.contentexport.egg-info/top_level.txt
src/collective/contentexport/__init__.py
src/collective/contentexport/configure.zcml
src/collective/contentexport/interfaces.py
src/collective/contentexport/setuphandlers.py
src/collective/contentexport/testing.py
src/collective/contentexport/browser/__init__.py
src/collective/contentexport/browser/configure.zcml
src/collective/contentexport/browser/export.py
src/collective/contentexport/browser/overrides/.gitkeep
src/collective/contentexport/browser/static/.gitkeep
src/collective/contentexport/browser/templates/export_form.pt
src/collective/contentexport/browser/templates/fieldnames.pt
src/collective/contentexport/locales/collective.contentexport.pot
src/collective/contentexport/locales/update.sh
src/collective/contentexport/locales/de/LC_MESSAGES/collective.contentexport.po
src/collective/contentexport/profiles/default/browserlayer.xml
src/collective/contentexport/profiles/default/controlpanel.xml
src/collective/contentexport/profiles/default/metadata.xml
src/collective/contentexport/profiles/uninstall/browserlayer.xml
src/collective/contentexport/profiles/uninstall/controlpanel.xml
src/collective/contentexport/tests/__init__.py
src/collective/contentexport/tests/image.png
src/collective/contentexport/tests/test_export.py
src/collective/contentexport/tests/test_setup.py