Metadata-Version: 1.1
Name: collective.contentexport
Version: 1.1
Summary: Plone add-on to export dexterity content in various formats
Home-page: https://pypi.python.org/pypi/collective.contentexport
Author: Philip Bauer
Author-email: bauer@starzel.de
License: GPL version 2
Keywords: Python Plone
Platform: UNKNOWN
Classifier: Environment :: Web Environment
Classifier: Framework :: Plone
Classifier: Framework :: Plone :: 4.3
Classifier: Framework :: Plone :: 5.0
Classifier: Framework :: Plone :: 5.1
Classifier: Programming Language :: Python
Classifier: Programming Language :: Python :: 2.7
Classifier: Operating System :: OS Independent
Classifier: License :: OSI Approved :: GNU General Public License v2 (GPLv2)
